percolate/__init__.py
percolate/settings.py
percolate/version.py
percolate/agents/__init__.py
percolate/agents/context.py
percolate/agents/factory.py
percolate/agents/registry.py
percolate/auth/__init__.py
percolate/auth/device.py
percolate/auth/jwt_manager.py
percolate/auth/middleware.py
percolate/auth/models.py
percolate/auth/oauth.py
percolate/cli/main.py
percolate/client/__init__.py
percolate/client/reading.py
percolate/mcp/__init__.py
percolate/mcp/resources.py
percolate/mcp/server.py
percolate/mcp/tools/__init__.py
percolate/mcp/tools/agent.py
percolate/mcp/tools/entity.py
percolate/mcp/tools/parse.py
percolate/mcp/tools/search.py
percolate_rem-0.1.0.dist-info/METADATA
percolate_rem-0.1.0.dist-info/WHEEL
percolate_rem-0.1.0.dist-info/entry_points.txt
percolate_rem-0.1.0.dist-info/RECORD
